flask_easyapi/__init__.py
flask_easyapi/flask_easyapi.py
flask_easyapi-0.1.1.dist-info/AUTHORS.rst
flask_easyapi-0.1.1.dist-info/LICENSE
flask_easyapi-0.1.1.dist-info/METADATA
flask_easyapi-0.1.1.dist-info/WHEEL
flask_easyapi-0.1.1.dist-info/top_level.txt
flask_easyapi-0.1.1.dist-info/RECORD
