Metadata-Version: 2.1
Name: flask-easyapi
Version: 0.1.1
Summary: Rest API on Flask made a little too easy.
Home-page: https://github.com/hXtreme/flask-easyapi
Author: Harsh Parekh
Author-email: harsh_parekh@outlook.com
License: MIT license
Keywords: flask_easyapi
Platform: UNKNOWN
Classifier: Framework :: Flask
Classifier: Development Status :: 2 - Pre-Alpha
Classifier: Environment :: Web Environment
Classifier: Intended Audience :: Developers
Classifier: License :: OSI Approved :: MIT License
Classifier: Operating System :: OS Independent
Classifier: Natural Language :: English
Classifier: Programming Language :: Python :: 3
Classifier: Programming Language :: Python :: 3.6
Classifier: Programming Language :: Python :: 3.7
Classifier: Programming Language :: Python :: 3.8
Classifier: Topic :: Internet :: WWW/HTTP :: Dynamic Content
Classifier: Topic :: Software Development :: Libraries :: Python Modules
Requires-Python: >=3.6
Requires-Dist: Flask (==1.1.2)
